scproximite/__init__.py
scproximite/funcs.py
scproximite-0.0.1.data/data/LICENSE
scproximite-0.0.1.dist-info/LICENSE
scproximite-0.0.1.dist-info/METADATA
scproximite-0.0.1.dist-info/WHEEL
scproximite-0.0.1.dist-info/entry_points.txt
scproximite-0.0.1.dist-info/top_level.txt
scproximite-0.0.1.dist-info/RECORD
