Metadata-Version: 2.1
Name: scproximite
Version: 0.0.1
Summary: UNKNOWN
Home-page: https://github.com/Ebony-Watson/scProximitE
Author: Ebony Watson
Author-email: ebonyrwatson@gmail.com
License: GPL3
Project-URL: Bug Tracker, https://github.com/Ebony-Watson/scProximitE/issues
Project-URL: Documentation, https://github.com/Ebony-Watson/scProximitE
Project-URL: Source Code, https://github.com/Ebony-Watson/scProximitE
Keywords: util
Platform: UNKNOWN
Classifier: Intended Audience :: Science/Research
Classifier: License :: OSI Approved :: GNU General Public License v3 (GPLv3)
Classifier: Natural Language :: English
Classifier: Operating System :: OS Independent
Classifier: Programming Language :: Python :: 3.6
Classifier: Programming Language :: Python :: 3.7
Classifier: Programming Language :: Python :: 3.8
Classifier: Topic :: Scientific/Engineering :: Bio-Informatics
Requires-Python: >=3.6
License-File: LICENSE
Requires-Dist: pandas
Requires-Dist: numpy
Requires-Dist: tensorflow
Requires-Dist: stats
Requires-Dist: seaborn
Requires-Dist: matplotlib
Requires-Dist: sklearn
Requires-Dist: jupyterlab
Requires-Dist: scanpy (==1.8.2)
Requires-Dist: sciviso
Requires-Dist: scikit-posthocs
Requires-Dist: torch
Requires-Dist: genieclust
Requires-Dist: natsort
Requires-Dist: leidenalg
